  { "nodeid": 0, "depth": 0, "split": "f6", "split_condition": -1.46983051, "yes": 1, "no": 2, "missing": 1 , "children": [
    { "nodeid": 1, "depth": 1, "split": "f6", "split_condition": -2.43487692, "yes": 3, "no": 4, "missing": 3 , "children": [
      { "nodeid": 3, "depth": 2, "split": "f1", "split_condition": 1.68361831, "yes": 7, "no": 8, "missing": 7 , "children": [
        { "nodeid": 7, "depth": 3, "split": "f17", "split_condition": 1.45612097, "yes": 15, "no": 16, "missing": 15 , "children": [
          { "nodeid": 15, "depth": 4, "split": "f19", "split_condition": 0.689925194, "yes": 29, "no": 30, "missing": 29 , "children": [
            { "nodeid": 29, "depth": 5, "split": "f15", "split_condition": -0.7003721, "yes": 55, "no": 56, "missing": 55 , "children": [
              { "nodeid": 55, "depth": 6, "split": "f10", "split_condition": 0.606724977, "yes": 99, "no": 100, "missing": 99 , "children": [
                { "nodeid": 99, "leaf": -2.46063519 }, 
                { "nodeid": 100, "leaf": -0.72702843 }
              ]}, 
              { "nodeid": 56, "depth": 6, "split": "f12", "split_condition": 0.246781066, "yes": 101, "no": 102, "missing": 101 , "children": [
                { "nodeid": 101, "depth": 7, "split": "f15", "split_condition": -0.231432393, "yes": 173, "no": 174, "missing": 173 , "children": [
                  { "nodeid": 173, "depth": 8, "split": "f0", "split_condition": 0.534931898, "yes": 287, "no": 288, "missing": 287 , "children": [
                    { "nodeid": 287, "depth": 9, "split": "f17", "split_condition": -0.906409144, "yes": 445, "no": 446, "missing": 445 , "children": [
                      { "nodeid": 445, "leaf": -0.147633687 }, 
                      { "nodeid": 446, "leaf": -0.737581134 }
                    ]}, 
                    { "nodeid": 288, "leaf": 0.125602722 }
                  ]}, 
                  { "nodeid": 174, "depth": 8, "split": "f2", "split_condition": 0.538992405, "yes": 289, "no": 290, "missing": 289 , "children": [
                    { "nodeid": 289, "depth": 9, "split": "f7", "split_condition": 0.760955215, "yes": 447, "no": 448, "missing": 447 , "children": [
                      { "nodeid": 447, "leaf": -1.8684746 }, 
                      { "nodeid": 448, "leaf": -0.6478495 }
                    ]}, 
                    { "nodeid": 290, "leaf": -0.426155716 }
                  ]}
                ]}, 
                { "nodeid": 102, "depth": 7, "split": "f10", "split_condition": 0.235692292, "yes": 175, "no": 176, "missing": 175 , "children": [
                  { "nodeid": 175, "depth": 8, "split": "f2", "split_condition": -0.0333060548, "yes": 291, "no": 292, "missing": 291 , "children": [
                    { "nodeid": 291, "leaf": -0.162564084 }, 
                    { "nodeid": 292, "leaf": -0.619209051 }
                  ]}, 
                  { "nodeid": 176, "depth": 8, "split": "f17", "split_condition": 0.611584365, "yes": 293, "no": 294, "missing": 293 , "children": [
                    { "nodeid": 293, "leaf": -0.192760259 }, 
                    { "nodeid": 294, "depth": 9, "split": "f0", "split_condition": 0.538361967, "yes": 449, "no": 450, "missing": 449 , "children": [
                      { "nodeid": 449, "leaf": 0.0921134949 }, 
                      { "nodeid": 450, "leaf": 0.0112747196 }
                    ]}
                  ]}
                ]}
              ]}
            ]}, 
            { "nodeid": 30, "depth": 5, "split": "f18", "split_condition": 0.65466243, "yes": 57, "no": 58, "missing": 57 , "children": [
              { "nodeid": 57, "depth": 6, "split": "f2", "split_condition": -0.314396173, "yes": 103, "no": 104, "missing": 103 , "children": [
                { "nodeid": 103, "depth": 7, "split": "f13", "split_condition": 0.0760154873, "yes": 177, "no": 178, "missing": 177 , "children": [
                  { "nodeid": 177, "leaf": 0.00376065564 }, 
                  { "nodeid": 178, "leaf": -0.299075693 }
                ]}, 
                { "nodeid": 104, "leaf": -0.854280949 }
              ]}, 
              { "nodeid": 58, "depth": 6, "split": "f0", "split_condition": -1.18266606, "yes": 105, "no": 106, "missing": 105 , "children": [
                { "nodeid": 105, "leaf": 0.0923099294 }, 
                { "nodeid": 106, "leaf": 0.479055732 }
              ]}
            ]}
          ]}, 
          { "nodeid": 16, "depth": 4, "split": "f10", "split_condition": -0.769198477, "yes": 31, "no": 32, "missing": 31 , "children": [
            { "nodeid": 31, "leaf": -0.0837209746 }, 
            { "nodeid": 32, "leaf": 0.275176495 }
          ]}
        ]}, 
        { "nodeid": 8, "depth": 3, "split": "f4", "split_condition": 1.00297606, "yes": 17, "no": 18, "missing": 17 , "children": [
          { "nodeid": 17, "depth": 4, "split": "f0", "split_condition": -0.875048399, "yes": 33, "no": 34, "missing": 33 , "children": [
            { "nodeid": 33, "leaf": 0.609985888 }, 
            { "nodeid": 34, "leaf": 0.205215454 }
          ]}, 
          { "nodeid": 18, "leaf": -0.162230685 }
        ]}
      ]}, 
      { "nodeid": 4, "depth": 2, "split": "f7", "split_condition": 2.69300127, "yes": 9, "no": 10, "missing": 9 , "children": [
        { "nodeid": 9, "depth": 3, "split": "f2", "split_condition": -0.499966413, "yes": 19, "no": 20, "missing": 19 , "children": [
          { "nodeid": 19, "depth": 4, "split": "f14", "split_condition": -0.805504262, "yes": 35, "no": 36, "missing": 35 , "children": [
            { "nodeid": 35, "depth": 5, "split": "f17", "split_condition": 0.759364128, "yes": 59, "no": 60, "missing": 59 , "children": [
              { "nodeid": 59, "depth": 6, "split": "f9", "split_condition": -0.519682169, "yes": 107, "no": 108, "missing": 107 , "children": [
                { "nodeid": 107, "depth": 7, "split": "f17", "split_condition": -1.3464514, "yes": 179, "no": 180, "missing": 179 , "children": [
                  { "nodeid": 179, "leaf": -0.301685065 }, 
                  { "nodeid": 180, "leaf": -1.83602428 }
                ]}, 
                { "nodeid": 108, "depth": 7, "split": "f1", "split_condition": 0.916353464, "yes": 181, "no": 182, "missing": 181 , "children": [
                  { "nodeid": 181, "depth": 8, "split": "f19", "split_condition": 1.22365594, "yes": 295, "no": 296, "missing": 295 , "children": [
                    { "nodeid": 295, "depth": 9, "split": "f14", "split_condition": -1.1416142, "yes": 451, "no": 452, "missing": 451 , "children": [
                      { "nodeid": 451, "leaf": -1.05167234 }, 
                      { "nodeid": 452, "leaf": -0.514692962 }
                    ]}, 
                    { "nodeid": 296, "leaf": -0.0243804939 }
                  ]}, 
                  { "nodeid": 182, "depth": 8, "split": "f0", "split_condition": -0.255979002, "yes": 297, "no": 298, "missing": 297 , "children": [
                    { "nodeid": 297, "leaf": -0.0972797424 }, 
                    { "nodeid": 298, "leaf": 0.083020024 }
                  ]}
                ]}
              ]}, 
              { "nodeid": 60, "depth": 6, "split": "f4", "split_condition": -0.666972756, "yes": 109, "no": 110, "missing": 109 , "children": [
                { "nodeid": 109, "depth": 7, "split": "f12", "split_condition": -0.441577852, "yes": 183, "no": 184, "missing": 183 , "children": [
                  { "nodeid": 183, "leaf": 0.484567255 }, 
                  { "nodeid": 184, "depth": 8, "split": "f2", "split_condition": -0.950562, "yes": 299, "no": 300, "missing": 299 , "children": [
                    { "nodeid": 299, "depth": 9, "split": "f0", "split_condition": 0.276264131, "yes": 453, "no": 454, "missing": 453 , "children": [
                      { "nodeid": 453, "leaf": -0.0118414564 }, 
                      { "nodeid": 454, "leaf": 0.0582960136 }
                    ]}, 
                    { "nodeid": 300, "leaf": -0.141820535 }
                  ]}
                ]}, 
                { "nodeid": 110, "depth": 7, "split": "f3", "split_condition": -1.84819913, "yes": 185, "no": 186, "missing": 185 , "children": [
                  { "nodeid": 185, "leaf": 0.0599426292 }, 
                  { "nodeid": 186, "leaf": -0.63273102 }
                ]}
              ]}
            ]}, 
            { "nodeid": 36, "depth": 5, "split": "f3", "split_condition": -0.116291061, "yes": 61, "no": 62, "missing": 61 , "children": [
              { "nodeid": 61, "depth": 6, "split": "f7", "split_condition": -0.60112834, "yes": 111, "no": 112, "missing": 111 , "children": [
                { "nodeid": 111, "depth": 7, "split": "f1", "split_condition": -0.221156716, "yes": 187, "no": 188, "missing": 187 , "children": [
                  { "nodeid": 187, "depth": 8, "split": "f0", "split_condition": -0.926065385, "yes": 301, "no": 302, "missing": 301 , "children": [
                    { "nodeid": 301, "leaf": -0.0965988189 }, 
                    { "nodeid": 302, "leaf": -1.97651672 }
                  ]}, 
                  { "nodeid": 188, "depth": 8, "split": "f4", "split_condition": -0.0225945041, "yes": 303, "no": 304, "missing": 303 , "children": [
                    { "nodeid": 303, "depth": 9, "split": "f0", "split_condition": -0.404079169, "yes": 455, "no": 456, "missing": 455 , "children": [
                      { "nodeid": 455, "leaf": 0.284891903 }, 
                      { "nodeid": 456, "leaf": -0.000970459019 }
                    ]}, 
                    { "nodeid": 304, "depth": 9, "split": "f0", "split_condition": -0.280534029, "yes": 457, "no": 458, "missing": 457 , "children": [
                      { "nodeid": 457, "leaf": -0.0878479034 }, 
                      { "nodeid": 458, "leaf": -0.49920249 }
                    ]}
                  ]}
                ]}, 
                { "nodeid": 112, "depth": 7, "split": "f0", "split_condition": -0.0377447717, "yes": 189, "no": 190, "missing": 189 , "children": [
                  { "nodeid": 189, "depth": 8, "split": "f1", "split_condition": 0.00824877992, "yes": 305, "no": 306, "missing": 305 , "children": [
                    { "nodeid": 305, "depth": 9, "split": "f3", "split_condition": -1.00541353, "yes": 459, "no": 460, "missing": 459 , "children": [
                      { "nodeid": 459, "leaf": -0.458697528 }, 
                      { "nodeid": 460, "leaf": 0.0811224952 }
                    ]}, 
                    { "nodeid": 306, "depth": 9, "split": "f10", "split_condition": -1.36224294, "yes": 461, "no": 462, "missing": 461 , "children": [
                      { "nodeid": 461, "leaf": -0.215779573 }, 
                      { "nodeid": 462, "leaf": -1.01409483 }
                    ]}
                  ]}, 
                  { "nodeid": 190, "depth": 8, "split": "f12", "split_condition": 1.48468018, "yes": 307, "no": 308, "missing": 307 , "children": [
                    { "nodeid": 307, "depth": 9, "split": "f17", "split_condition": -0.239348829, "yes": 463, "no": 464, "missing": 463 , "children": [
                      { "nodeid": 463, "leaf": -0.544551551 }, 
                      { "nodeid": 464, "leaf": 0.0302389544 }
                    ]}, 
                    { "nodeid": 308, "leaf": 0.57903558 }
                  ]}
                ]}
              ]}, 
              { "nodeid": 62, "depth": 6, "split": "f12", "split_condition": -0.714226246, "yes": 113, "no": 114, "missing": 113 , "children": [
                { "nodeid": 113, "depth": 7, "split": "f2", "split_condition": -0.643406034, "yes": 191, "no": 192, "missing": 191 , "children": [
                  { "nodeid": 191, "depth": 8, "split": "f14", "split_condition": 0.468163252, "yes": 309, "no": 310, "missing": 309 , "children": [
                    { "nodeid": 309, "depth": 9, "split": "f12", "split_condition": -0.978543162, "yes": 465, "no": 466, "missing": 465 , "children": [
                      { "nodeid": 465, "leaf": -0.524018228 }, 
                      { "nodeid": 466, "leaf": -1.24000823 }
                    ]}, 
                    { "nodeid": 310, "depth": 9, "split": "f9", "split_condition": 0.722200155, "yes": 467, "no": 468, "missing": 467 , "children": [
                      { "nodeid": 467, "leaf": 0.00673789997 }, 
                      { "nodeid": 468, "leaf": -0.390277982 }
                    ]}
                  ]}, 
                  { "nodeid": 192, "depth": 8, "split": "f0", "split_condition": 0.549465775, "yes": 311, "no": 312, "missing": 311 , "children": [
                    { "nodeid": 311, "leaf": 0.0390335098 }, 
                    { "nodeid": 312, "leaf": 0.628832996 }
                  ]}
                ]}, 
                { "nodeid": 114, "depth": 7, "split": "f12", "split_condition": 0.441384763, "yes": 193, "no": 194, "missing": 193 , "children": [
                  { "nodeid": 193, "depth": 8, "split": "f7", "split_condition": -0.0440661013, "yes": 313, "no": 314, "missing": 313 , "children": [
                    { "nodeid": 313, "depth": 9, "split": "f7", "split_condition": -0.825495183, "yes": 469, "no": 470, "missing": 469 , "children": [
                      { "nodeid": 469, "leaf": 0.0891979262 }, 
                      { "nodeid": 470, "leaf": -0.368892998 }
                    ]}, 
                    { "nodeid": 314, "depth": 9, "split": "f19", "split_condition": -0.3237409, "yes": 471, "no": 472, "missing": 471 , "children": [
                      { "nodeid": 471, "leaf": 0.497535557 }, 
                      { "nodeid": 472, "leaf": 0.0675537214 }
                    ]}
                  ]}, 
                  { "nodeid": 194, "depth": 8, "split": "f7", "split_condition": -1.02216434, "yes": 315, "no": 316, "missing": 315 , "children": [
                    { "nodeid": 315, "leaf": 0.450933278 }, 
                    { "nodeid": 316, "depth": 9, "split": "f17", "split_condition": 0.696918786, "yes": 473, "no": 474, "missing": 473 , "children": [
                      { "nodeid": 473, "leaf": -0.583374441 }, 
                      { "nodeid": 474, "leaf": 0.00260624895 }
                    ]}
                  ]}
                ]}
              ]}
            ]}
          ]}, 
          { "nodeid": 20, "depth": 4, "split": "f18", "split_condition": -2.46396351, "yes": 37, "no": 38, "missing": 37 , "children": [
            { "nodeid": 37, "depth": 5, "split": "f0", "split_condition": -0.924936414, "yes": 63, "no": 64, "missing": 63 , "children": [
              { "nodeid": 63, "depth": 6, "split": "f0", "split_condition": -1.19469762, "yes": 115, "no": 116, "missing": 115 , "children": [
                { "nodeid": 115, "leaf": -0.280127734 }, 
                { "nodeid": 116, "leaf": 0.0772533938 }
              ]}, 
              { "nodeid": 64, "leaf": -1.4499656 }
            ]}, 
            { "nodeid": 38, "depth": 5, "split": "f4", "split_condition": 0.356910735, "yes": 65, "no": 66, "missing": 65 , "children": [
              { "nodeid": 65, "depth": 6, "split": "f6", "split_condition": -1.49948788, "yes": 117, "no": 118, "missing": 117 , "children": [
                { "nodeid": 117, "depth": 7, "split": "f4", "split_condition": 0.055800125, "yes": 195, "no": 196, "missing": 195 , "children": [
                  { "nodeid": 195, "depth": 8, "split": "f9", "split_condition": -0.339638948, "yes": 317, "no": 318, "missing": 317 , "children": [
                    { "nodeid": 317, "depth": 9, "split": "f7", "split_condition": 0.782074809, "yes": 475, "no": 476, "missing": 475 , "children": [
                      { "nodeid": 475, "leaf": -0.411147743 }, 
                      { "nodeid": 476, "leaf": 0.207155034 }
                    ]}, 
                    { "nodeid": 318, "depth": 9, "split": "f4", "split_condition": -0.915437102, "yes": 477, "no": 478, "missing": 477 , "children": [
                      { "nodeid": 477, "leaf": -0.180571616 }, 
                      { "nodeid": 478, "leaf": 0.259861559 }
                    ]}
                  ]}, 
                  { "nodeid": 196, "depth": 8, "split": "f7", "split_condition": -1.51646566, "yes": 319, "no": 320, "missing": 319 , "children": [
                    { "nodeid": 319, "depth": 9, "split": "f4", "split_condition": 0.300783664, "yes": 479, "no": 480, "missing": 479 , "children": [
                      { "nodeid": 479, "leaf": 0.620767236 }, 
                      { "nodeid": 480, "leaf": -0.0047035981 }
                    ]}, 
                    { "nodeid": 320, "depth": 9, "split": "f18", "split_condition": 1.4972496, "yes": 481, "no": 482, "missing": 481 , "children": [
                      { "nodeid": 481, "leaf": -0.785550892 }, 
                      { "nodeid": 482, "leaf": 0.0888039246 }
                    ]}
                  ]}
                ]}, 
                { "nodeid": 118, "depth": 7, "split": "f1", "split_condition": 0.276209354, "yes": 197, "no": 198, "missing": 197 , "children": [
                  { "nodeid": 197, "depth": 8, "split": "f15", "split_condition": -0.18731609, "yes": 321, "no": 322, "missing": 321 , "children": [
                    { "nodeid": 321, "leaf": -1.70151258 }, 
                    { "nodeid": 322, "depth": 9, "split": "f14", "split_condition": 0.33248651, "yes": 483, "no": 484, "missing": 483 , "children": [
                      { "nodeid": 483, "leaf": -0.681782663 }, 
                      { "nodeid": 484, "leaf": -0.110139482 }
                    ]}
                  ]}, 
                  { "nodeid": 198, "depth": 8, "split": "f14", "split_condition": -0.512361944, "yes": 323, "no": 324, "missing": 323 , "children": [
                    { "nodeid": 323, "depth": 9, "split": "f0", "split_condition": 0.0678006783, "yes": 485, "no": 486, "missing": 485 , "children": [
                      { "nodeid": 485, "leaf": -0.0383300781 }, 
                      { "nodeid": 486, "leaf": 0.221748859 }
                    ]}, 
                    { "nodeid": 324, "depth": 9, "split": "f0", "split_condition": 0.838760495, "yes": 487, "no": 488, "missing": 487 , "children": [
                      { "nodeid": 487, "leaf": -0.749637604 }, 
                      { "nodeid": 488, "leaf": 0.0529636405 }
                    ]}
                  ]}
                ]}
              ]}, 
              { "nodeid": 66, "depth": 6, "split": "f12", "split_condition": -1.01445174, "yes": 119, "no": 120, "missing": 119 , "children": [
                { "nodeid": 119, "depth": 7, "split": "f2", "split_condition": 0.40555656, "yes": 199, "no": 200, "missing": 199 , "children": [
                  { "nodeid": 199, "depth": 8, "split": "f2", "split_condition": 0.00661206618, "yes": 325, "no": 326, "missing": 325 , "children": [
                    { "nodeid": 325, "leaf": -0.557442129 }, 
                    { "nodeid": 326, "leaf": -1.72165966 }
                  ]}, 
                  { "nodeid": 200, "depth": 8, "split": "f2", "split_condition": 0.570907891, "yes": 327, "no": 328, "missing": 327 , "children": [
                    { "nodeid": 327, "depth": 9, "split": "f0", "split_condition": 0.89353478, "yes": 489, "no": 490, "missing": 489 , "children": [
                      { "nodeid": 489, "leaf": 0.25884819 }, 
                      { "nodeid": 490, "leaf": 0.0418075584 }
                    ]}, 
                    { "nodeid": 328, "depth": 9, "split": "f0", "split_condition": -0.801951766, "yes": 491, "no": 492, "missing": 491 , "children": [
                      { "nodeid": 491, "leaf": 0.157524496 }, 
                      { "nodeid": 492, "leaf": -0.198989764 }
                    ]}
                  ]}
                ]}, 
                { "nodeid": 120, "depth": 7, "split": "f17", "split_condition": -0.605875134, "yes": 201, "no": 202, "missing": 201 , "children": [
                  { "nodeid": 201, "depth": 8, "split": "f3", "split_condition": 1.26939178, "yes": 329, "no": 330, "missing": 329 , "children": [
                    { "nodeid": 329, "depth": 9, "split": "f17", "split_condition": -0.870217621, "yes": 493, "no": 494, "missing": 493 , "children": [
                      { "nodeid": 493, "leaf": -0.109999992 }, 
                      { "nodeid": 494, "leaf": -0.670985818 }
                    ]}, 
                    { "nodeid": 330, "depth": 9, "split": "f9", "split_condition": 0.138200149, "yes": 495, "no": 496, "missing": 495 , "children": [
                      { "nodeid": 495, "leaf": -0.142001346 }, 
                      { "nodeid": 496, "leaf": 0.563170612 }
                    ]}
                  ]}, 
                  { "nodeid": 202, "depth": 8, "split": "f17", "split_condition": 0.0257927887, "yes": 331, "no": 332, "missing": 331 , "children": [
                    { "nodeid": 331, "depth": 9, "split": "f15", "split_condition": -1.59278488, "yes": 497, "no": 498, "missing": 497 , "children": [
                      { "nodeid": 497, "leaf": -0.570053101 }, 
                      { "nodeid": 498, "leaf": 0.580022633 }
                    ]}, 
                    { "nodeid": 332, "depth": 9, "split": "f17", "split_condition": 0.357542038, "yes": 499, "no": 500, "missing": 499 , "children": [
                      { "nodeid": 499, "leaf": -0.159309745 }, 
                      { "nodeid": 500, "leaf": 0.216446593 }
                    ]}
                  ]}
                ]}
              ]}
            ]}
          ]}
        ]}, 
        { "nodeid": 10, "leaf": 1.8054924 }
      ]}
    ]}, 
    { "nodeid": 2, "depth": 1, "split": "f14", "split_condition": -1.63250637, "yes": 5, "no": 6, "missing": 5 , "children": [
      { "nodeid": 5, "depth": 2, "split": "f14", "split_condition": -2.34315443, "yes": 11, "no": 12, "missing": 11 , "children": [
        { "nodeid": 11, "depth": 3, "split": "f19", "split_condition": 0.438794017, "yes": 21, "no": 22, "missing": 21 , "children": [
          { "nodeid": 21, "depth": 4, "split": "f7", "split_condition": 1.94060087, "yes": 39, "no": 40, "missing": 39 , "children": [
            { "nodeid": 39, "depth": 5, "split": "f13", "split_condition": -1.7597301, "yes": 67, "no": 68, "missing": 67 , "children": [
              { "nodeid": 67, "depth": 6, "split": "f1", "split_condition": 0.257815093, "yes": 121, "no": 122, "missing": 121 , "children": [
                { "nodeid": 121, "depth": 7, "split": "f0", "split_condition": 0.6564973, "yes": 203, "no": 204, "missing": 203 , "children": [
                  { "nodeid": 203, "leaf": 0.0101913456 }, 
                  { "nodeid": 204, "leaf": 0.251967818 }
                ]}, 
                { "nodeid": 122, "leaf": -0.393914789 }
              ]}, 
              { "nodeid": 68, "depth": 6, "split": "f4", "split_condition": 1.1042161, "yes": 123, "no": 124, "missing": 123 , "children": [
                { "nodeid": 123, "depth": 7, "split": "f4", "split_condition": 0.697825789, "yes": 205, "no": 206, "missing": 205 , "children": [
                  { "nodeid": 205, "depth": 8, "split": "f1", "split_condition": 1.88714981, "yes": 333, "no": 334, "missing": 333 , "children": [
                    { "nodeid": 333, "depth": 9, "split": "f13", "split_condition": -1.22765934, "yes": 501, "no": 502, "missing": 501 , "children": [
                      { "nodeid": 501, "leaf": -0.180355072 }, 
                      { "nodeid": 502, "leaf": -1.04795444 }
                    ]}, 
                    { "nodeid": 334, "leaf": -0.154942319 }
                  ]}, 
                  { "nodeid": 206, "leaf": -2.07942247 }
                ]}, 
                { "nodeid": 124, "depth": 7, "split": "f7", "split_condition": 0.137679055, "yes": 207, "no": 208, "missing": 207 , "children": [
                  { "nodeid": 207, "depth": 8, "split": "f0", "split_condition": -0.472486854, "yes": 335, "no": 336, "missing": 335 , "children": [
                    { "nodeid": 335, "leaf": -0.0458648689 }, 
                    { "nodeid": 336, "leaf": 0.182613373 }
                  ]}, 
                  { "nodeid": 208, "leaf": -0.651930749 }
                ]}
              ]}
            ]}, 
            { "nodeid": 40, "depth": 5, "split": "f0", "split_condition": -0.234154999, "yes": 69, "no": 70, "missing": 69 , "children": [
              { "nodeid": 69, "leaf": 0.487030029 }, 
              { "nodeid": 70, "leaf": 0.00230712886 }
            ]}
          ]}, 
          { "nodeid": 22, "depth": 4, "split": "f7", "split_condition": -0.105984554, "yes": 41, "no": 42, "missing": 41 , "children": [
            { "nodeid": 41, "depth": 5, "split": "f6", "split_condition": 1.58971262, "yes": 71, "no": 72, "missing": 71 , "children": [
              { "nodeid": 71, "depth": 6, "split": "f9", "split_condition": 1.24290931, "yes": 125, "no": 126, "missing": 125 , "children": [
                { "nodeid": 125, "depth": 7, "split": "f1", "split_condition": -1.48555708, "yes": 209, "no": 210, "missing": 209 , "children": [
                  { "nodeid": 209, "leaf": -0.179154977 }, 
                  { "nodeid": 210, "leaf": -1.06591856 }
                ]}, 
                { "nodeid": 126, "depth": 7, "split": "f0", "split_condition": 0.598748326, "yes": 211, "no": 212, "missing": 211 , "children": [
                  { "nodeid": 211, "leaf": -0.209418923 }, 
                  { "nodeid": 212, "leaf": 0.012078858 }
                ]}
              ]}, 
              { "nodeid": 72, "leaf": 0.169897079 }
            ]}, 
            { "nodeid": 42, "depth": 5, "split": "f19", "split_condition": 0.586357951, "yes": 73, "no": 74, "missing": 73 , "children": [
              { "nodeid": 73, "leaf": 0.509372175 }, 
              { "nodeid": 74, "depth": 6, "split": "f7", "split_condition": 0.821914196, "yes": 127, "no": 128, "missing": 127 , "children": [
                { "nodeid": 127, "depth": 7, "split": "f3", "split_condition": 1.11190653, "yes": 213, "no": 214, "missing": 213 , "children": [
                  { "nodeid": 213, "leaf": -0.579178393 }, 
                  { "nodeid": 214, "leaf": -0.128506467 }
                ]}, 
                { "nodeid": 128, "depth": 7, "split": "f15", "split_condition": -0.719854057, "yes": 215, "no": 216, "missing": 215 , "children": [
                  { "nodeid": 215, "depth": 8, "split": "f0", "split_condition": -0.577392519, "yes": 337, "no": 338, "missing": 337 , "children": [
                    { "nodeid": 337, "leaf": 0.0329376236 }, 
                    { "nodeid": 338, "leaf": 0.124283217 }
                  ]}, 
                  { "nodeid": 216, "depth": 8, "split": "f7", "split_condition": 1.03094959, "yes": 339, "no": 340, "missing": 339 , "children": [
                    { "nodeid": 339, "depth": 9, "split": "f0", "split_condition": -0.186434478, "yes": 503, "no": 504, "missing": 503 , "children": [
                      { "nodeid": 503, "leaf": -0.00702614803 }, 
                      { "nodeid": 504, "leaf": 0.029191589 }
                    ]}, 
                    { "nodeid": 340, "leaf": -0.0916011557 }
                  ]}
                ]}
              ]}
            ]}
          ]}
        ]}, 
        { "nodeid": 12, "depth": 3, "split": "f17", "split_condition": -0.619091392, "yes": 23, "no": 24, "missing": 23 , "children": [
          { "nodeid": 23, "depth": 4, "split": "f17", "split_condition": -0.703434348, "yes": 43, "no": 44, "missing": 43 , "children": [
            { "nodeid": 43, "depth": 5, "split": "f7", "split_condition": 0.414473593, "yes": 75, "no": 76, "missing": 75 , "children": [
              { "nodeid": 75, "depth": 6, "split": "f4", "split_condition": 0.939763188, "yes": 129, "no": 130, "missing": 129 , "children": [
                { "nodeid": 129, "depth": 7, "split": "f18", "split_condition": 0.419943064, "yes": 217, "no": 218, "missing": 217 , "children": [
                  { "nodeid": 217, "depth": 8, "split": "f10", "split_condition": 0.740392447, "yes": 341, "no": 342, "missing": 341 , "children": [
                    { "nodeid": 341, "depth": 9, "split": "f2", "split_condition": 1.61562371, "yes": 505, "no": 506, "missing": 505 , "children": [
                      { "nodeid": 505, "leaf": -1.58218765 }, 
                      { "nodeid": 506, "leaf": 0.218012244 }
                    ]}, 
                    { "nodeid": 342, "depth": 9, "split": "f0", "split_condition": 0.324965268, "yes": 507, "no": 508, "missing": 507 , "children": [
                      { "nodeid": 507, "leaf": 0.285569012 }, 
                      { "nodeid": 508, "leaf": -0.1926478 }
                    ]}
                  ]}, 
                  { "nodeid": 218, "depth": 8, "split": "f18", "split_condition": 0.638648331, "yes": 343, "no": 344, "missing": 343 , "children": [
                    { "nodeid": 343, "depth": 9, "split": "f3", "split_condition": -0.216571942, "yes": 509, "no": 510, "missing": 509 , "children": [
                      { "nodeid": 509, "leaf": 0.0175381973 }, 
                      { "nodeid": 510, "leaf": 0.235179901 }
                    ]}, 
                    { "nodeid": 344, "depth": 9, "split": "f10", "split_condition": -0.494322211, "yes": 511, "no": 512, "missing": 511 , "children": [
                      { "nodeid": 511, "leaf": -0.222435758 }, 
                      { "nodeid": 512, "leaf": -0.870503128 }
                    ]}
                  ]}
                ]}, 
                { "nodeid": 130, "depth": 7, "split": "f1", "split_condition": 0.872555137, "yes": 219, "no": 220, "missing": 219 , "children": [
                  { "nodeid": 219, "depth": 8, "split": "f0", "split_condition": -0.343802124, "yes": 345, "no": 346, "missing": 345 , "children": [
                    { "nodeid": 345, "depth": 9, "split": "f0", "split_condition": -0.422011107, "yes": 513, "no": 514, "missing": 513 , "children": [
                      { "nodeid": 513, "leaf": 0.160490423 }, 
                      { "nodeid": 514, "leaf": 0.0301208496 }
                    ]}, 
                    { "nodeid": 346, "depth": 9, "split": "f7", "split_condition": -0.494795084, "yes": 515, "no": 516, "missing": 515 , "children": [
                      { "nodeid": 515, "leaf": -0.120212413 }, 
                      { "nodeid": 516, "leaf": -0.420531482 }
                    ]}
                  ]}, 
                  { "nodeid": 220, "leaf": 0.394232959 }
                ]}
              ]}, 
              { "nodeid": 76, "depth": 6, "split": "f1", "split_condition": -0.197182089, "yes": 131, "no": 132, "missing": 131 , "children": [
                { "nodeid": 131, "depth": 7, "split": "f7", "split_condition": 0.737494349, "yes": 221, "no": 222, "missing": 221 , "children": [
                  { "nodeid": 221, "depth": 8, "split": "f3", "split_condition": -0.647806704, "yes": 347, "no": 348, "missing": 347 , "children": [
                    { "nodeid": 347, "leaf": 0.266422272 }, 
                    { "nodeid": 348, "leaf": 0.780041158 }
                  ]}, 
                  { "nodeid": 222, "depth": 8, "split": "f0", "split_condition": -0.209773615, "yes": 349, "no": 350, "missing": 349 , "children": [
                    { "nodeid": 349, "depth": 9, "split": "f0", "split_condition": -0.871362448, "yes": 517, "no": 518, "missing": 517 , "children": [
                      { "nodeid": 517, "leaf": 0.165008679 }, 
                      { "nodeid": 518, "leaf": -0.0157368984 }
                    ]}, 
                    { "nodeid": 350, "leaf": -0.454532862 }
                  ]}
                ]}, 
                { "nodeid": 132, "depth": 7, "split": "f10", "split_condition": 0.443809956, "yes": 223, "no": 224, "missing": 223 , "children": [
                  { "nodeid": 223, "leaf": -0.517905772 }, 
                  { "nodeid": 224, "depth": 8, "split": "f0", "split_condition": -0.993582606, "yes": 351, "no": 352, "missing": 351 , "children": [
                    { "nodeid": 351, "leaf": -0.0430366509 }, 
                    { "nodeid": 352, "leaf": -0.166629106 }
                  ]}
                ]}
              ]}
            ]}, 
            { "nodeid": 44, "depth": 5, "split": "f0", "split_condition": 0.809625626, "yes": 77, "no": 78, "missing": 77 , "children": [
              { "nodeid": 77, "depth": 6, "split": "f2", "split_condition": 0.580337763, "yes": 133, "no": 134, "missing": 133 , "children": [
                { "nodeid": 133, "leaf": -1.88857138 }, 
                { "nodeid": 134, "leaf": -0.437541217 }
              ]}, 
              { "nodeid": 78, "leaf": -0.0467195511 }
            ]}
          ]}, 
          { "nodeid": 24, "depth": 4, "split": "f3", "split_condition": 1.49266982, "yes": 45, "no": 46, "missing": 45 , "children": [
            { "nodeid": 45, "depth": 5, "split": "f14", "split_condition": -1.65400815, "yes": 79, "no": 80, "missing": 79 , "children": [
              { "nodeid": 79, "depth": 6, "split": "f9", "split_condition": -1.26136792, "yes": 135, "no": 136, "missing": 135 , "children": [
                { "nodeid": 135, "depth": 7, "split": "f4", "split_condition": -0.319480419, "yes": 225, "no": 226, "missing": 225 , "children": [
                  { "nodeid": 225, "depth": 8, "split": "f0", "split_condition": 0.264341474, "yes": 353, "no": 354, "missing": 353 , "children": [
                    { "nodeid": 353, "leaf": -1.33286655 }, 
                    { "nodeid": 354, "leaf": -0.302822381 }
                  ]}, 
                  { "nodeid": 226, "depth": 8, "split": "f2", "split_condition": -0.0125462562, "yes": 355, "no": 356, "missing": 355 , "children": [
                    { "nodeid": 355, "depth": 9, "split": "f0", "split_condition": -0.936190248, "yes": 519, "no": 520, "missing": 519 , "children": [
                      { "nodeid": 519, "leaf": -0.0956130996 }, 
                      { "nodeid": 520, "leaf": -0.386615485 }
                    ]}, 
                    { "nodeid": 356, "depth": 9, "split": "f0", "split_condition": 0.627427161, "yes": 521, "no": 522, "missing": 521 , "children": [
                      { "nodeid": 521, "leaf": 0.00641212473 }, 
                      { "nodeid": 522, "leaf": 0.149257615 }
                    ]}
                  ]}
                ]}, 
                { "nodeid": 136, "depth": 7, "split": "f7", "split_condition": -2.30014277, "yes": 227, "no": 228, "missing": 227 , "children": [
                  { "nodeid": 227, "leaf": -1.12770545 }, 
                  { "nodeid": 228, "depth": 8, "split": "f14", "split_condition": -1.70179725, "yes": 357, "no": 358, "missing": 357 , "children": [
                    { "nodeid": 357, "depth": 9, "split": "f1", "split_condition": -0.720678568, "yes": 523, "no": 524, "missing": 523 , "children": [
                      { "nodeid": 523, "leaf": 0.179261625 }, 
                      { "nodeid": 524, "leaf": -0.17382513 }
                    ]}, 
                    { "nodeid": 358, "depth": 9, "split": "f14", "split_condition": -1.69298923, "yes": 525, "no": 526, "missing": 525 , "children": [
                      { "nodeid": 525, "leaf": 0.839212418 }, 
                      { "nodeid": 526, "leaf": 0.124879673 }
                    ]}
                  ]}
                ]}
              ]}, 
              { "nodeid": 80, "depth": 6, "split": "f2", "split_condition": 1.70834374, "yes": 137, "no": 138, "missing": 137 , "children": [
                { "nodeid": 137, "depth": 7, "split": "f0", "split_condition": 1.57753015, "yes": 229, "no": 230, "missing": 229 , "children": [
                  { "nodeid": 229, "leaf": -1.12691498 }, 
                  { "nodeid": 230, "leaf": -0.219288632 }
                ]}, 
                { "nodeid": 138, "leaf": 0.339803308 }
              ]}
            ]}, 
            { "nodeid": 46, "depth": 5, "split": "f9", "split_condition": -0.60138309, "yes": 81, "no": 82, "missing": 81 , "children": [
              { "nodeid": 81, "depth": 6, "split": "f3", "split_condition": 1.61907721, "yes": 139, "no": 140, "missing": 139 , "children": [
                { "nodeid": 139, "leaf": 0.387473047 }, 
                { "nodeid": 140, "depth": 7, "split": "f0", "split_condition": -0.579530239, "yes": 231, "no": 232, "missing": 231 , "children": [
                  { "nodeid": 231, "leaf": -0.0643289462 }, 
                  { "nodeid": 232, "leaf": -0.0136711122 }
                ]}
              ]}, 
              { "nodeid": 82, "depth": 6, "split": "f0", "split_condition": -1.48811543, "yes": 141, "no": 142, "missing": 141 , "children": [
                { "nodeid": 141, "leaf": 0.255260468 }, 
                { "nodeid": 142, "leaf": 1.21831155 }
              ]}
            ]}
          ]}
        ]}
      ]}, 
      { "nodeid": 6, "depth": 2, "split": "f9", "split_condition": -0.86485219, "yes": 13, "no": 14, "missing": 13 , "children": [
        { "nodeid": 13, "depth": 3, "split": "f9", "split_condition": -2.5988431, "yes": 25, "no": 26, "missing": 25 , "children": [
          { "nodeid": 25, "depth": 4, "split": "f6", "split_condition": 0.54586339, "yes": 47, "no": 48, "missing": 47 , "children": [
            { "nodeid": 47, "depth": 5, "split": "f14", "split_condition": 0.75626874, "yes": 83, "no": 84, "missing": 83 , "children": [
              { "nodeid": 83, "depth": 6, "split": "f7", "split_condition": 1.02462673, "yes": 143, "no": 144, "missing": 143 , "children": [
                { "nodeid": 143, "depth": 7, "split": "f4", "split_condition": -0.200469255, "yes": 233, "no": 234, "missing": 233 , "children": [
                  { "nodeid": 233, "leaf": -0.841681421 }, 
                  { "nodeid": 234, "leaf": -1.93976152 }
                ]}, 
                { "nodeid": 144, "depth": 7, "split": "f3", "split_condition": -1.30612195, "yes": 235, "no": 236, "missing": 235 , "children": [
                  { "nodeid": 235, "leaf": 0.0238834377 }, 
                  { "nodeid": 236, "leaf": -0.681730807 }
                ]}
              ]}, 
              { "nodeid": 84, "depth": 6, "split": "f3", "split_condition": 0.357167244, "yes": 145, "no": 146, "missing": 145 , "children": [
                { "nodeid": 145, "depth": 7, "split": "f0", "split_condition": 0.901545048, "yes": 237, "no": 238, "missing": 237 , "children": [
                  { "nodeid": 237, "depth": 8, "split": "f2", "split_condition": 1.86051893, "yes": 359, "no": 360, "missing": 359 , "children": [
                    { "nodeid": 359, "leaf": -0.235370904 }, 
                    { "nodeid": 360, "leaf": -0.0418395996 }
                  ]}, 
                  { "nodeid": 238, "leaf": 0.0233306885 }
                ]}, 
                { "nodeid": 146, "leaf": -0.639753401 }
              ]}
            ]}, 
            { "nodeid": 48, "depth": 5, "split": "f18", "split_condition": -0.38584432, "yes": 85, "no": 86, "missing": 85 , "children": [
              { "nodeid": 85, "leaf": 0.294722497 }, 
              { "nodeid": 86, "depth": 6, "split": "f1", "split_condition": -0.905134499, "yes": 147, "no": 148, "missing": 147 , "children": [
                { "nodeid": 147, "leaf": 0.0220397953 }, 
                { "nodeid": 148, "leaf": -0.515395343 }
              ]}
            ]}
          ]}, 
          { "nodeid": 26, "depth": 4, "split": "f19", "split_condition": 0.859662235, "yes": 49, "no": 50, "missing": 49 , "children": [
            { "nodeid": 49, "depth": 5, "split": "f1", "split_condition": 1.56440496, "yes": 87, "no": 88, "missing": 87 , "children": [
              { "nodeid": 87, "depth": 6, "split": "f14", "split_condition": 1.0000602, "yes": 149, "no": 150, "missing": 149 , "children": [
                { "nodeid": 149, "depth": 7, "split": "f7", "split_condition": 0.897062421, "yes": 239, "no": 240, "missing": 239 , "children": [
                  { "nodeid": 239, "depth": 8, "split": "f4", "split_condition": 0.747522593, "yes": 361, "no": 362, "missing": 361 , "children": [
                    { "nodeid": 361, "depth": 9, "split": "f6", "split_condition": 0.140011698, "yes": 527, "no": 528, "missing": 527 , "children": [
                      { "nodeid": 527, "leaf": -0.525799215 }, 
                      { "nodeid": 528, "leaf": -0.240087822 }
                    ]}, 
                    { "nodeid": 362, "depth": 9, "split": "f19", "split_condition": 0.442923307, "yes": 529, "no": 530, "missing": 529 , "children": [
                      { "nodeid": 529, "leaf": -0.145924196 }, 
                      { "nodeid": 530, "leaf": 0.494058937 }
                    ]}
                  ]}, 
                  { "nodeid": 240, "depth": 8, "split": "f10", "split_condition": -0.154942155, "yes": 363, "no": 364, "missing": 363 , "children": [
                    { "nodeid": 363, "depth": 9, "split": "f2", "split_condition": -0.359289259, "yes": 531, "no": 532, "missing": 531 , "children": [
                      { "nodeid": 531, "leaf": -0.243906289 }, 
                      { "nodeid": 532, "leaf": 0.384198993 }
                    ]}, 
                    { "nodeid": 364, "depth": 9, "split": "f10", "split_condition": -0.122195698, "yes": 533, "no": 534, "missing": 533 , "children": [
                      { "nodeid": 533, "leaf": -1.05888498 }, 
                      { "nodeid": 534, "leaf": -0.083438389 }
                    ]}
                  ]}
                ]}, 
                { "nodeid": 150, "depth": 7, "split": "f10", "split_condition": 0.12220446, "yes": 241, "no": 242, "missing": 241 , "children": [
                  { "nodeid": 241, "depth": 8, "split": "f15", "split_condition": 1.41195798, "yes": 365, "no": 366, "missing": 365 , "children": [
                    { "nodeid": 365, "depth": 9, "split": "f19", "split_condition": -0.500020325, "yes": 535, "no": 536, "missing": 535 , "children": [
                      { "nodeid": 535, "leaf": 0.172772855 }, 
                      { "nodeid": 536, "leaf": -0.379115134 }
                    ]}, 
                    { "nodeid": 366, "depth": 9, "split": "f6", "split_condition": 0.642751932, "yes": 537, "no": 538, "missing": 537 , "children": [
                      { "nodeid": 537, "leaf": 0.70271486 }, 
                      { "nodeid": 538, "leaf": -0.101264 }
                    ]}
                  ]}, 
                  { "nodeid": 242, "depth": 8, "split": "f19", "split_condition": -0.418466598, "yes": 367, "no": 368, "missing": 367 , "children": [
                    { "nodeid": 367, "depth": 9, "split": "f18", "split_condition": -0.480937093, "yes": 539, "no": 540, "missing": 539 , "children": [
                      { "nodeid": 539, "leaf": -0.313381672 }, 
                      { "nodeid": 540, "leaf": 0.0950584486 }
                    ]}, 
                    { "nodeid": 368, "depth": 9, "split": "f4", "split_condition": -0.382207692, "yes": 541, "no": 542, "missing": 541 , "children": [
                      { "nodeid": 541, "leaf": 0.890797913 }, 
                      { "nodeid": 542, "leaf": 0.200234935 }
                    ]}
                  ]}
                ]}
              ]}, 
              { "nodeid": 88, "depth": 6, "split": "f7", "split_condition": 0.45565027, "yes": 151, "no": 152, "missing": 151 , "children": [
                { "nodeid": 151, "depth": 7, "split": "f0", "split_condition": 1.55975413, "yes": 243, "no": 244, "missing": 243 , "children": [
                  { "nodeid": 243, "depth": 8, "split": "f17", "split_condition": -0.869193792, "yes": 369, "no": 370, "missing": 369 , "children": [
                    { "nodeid": 369, "depth": 9, "split": "f17", "split_condition": -1.62395513, "yes": 543, "no": 544, "missing": 543 , "children": [
                      { "nodeid": 543, "leaf": -0.0820381939 }, 
                      { "nodeid": 544, "leaf": 0.499347121 }
                    ]}, 
                    { "nodeid": 370, "depth": 9, "split": "f2", "split_condition": -0.755292475, "yes": 545, "no": 546, "missing": 545 , "children": [
                      { "nodeid": 545, "leaf": 0.302985072 }, 
                      { "nodeid": 546, "leaf": -0.311659276 }
                    ]}
                  ]}, 
                  { "nodeid": 244, "leaf": 1.38568115 }
                ]}, 
                { "nodeid": 152, "depth": 7, "split": "f10", "split_condition": 0.164609998, "yes": 245, "no": 246, "missing": 245 , "children": [
                  { "nodeid": 245, "depth": 8, "split": "f15", "split_condition": -0.851172388, "yes": 371, "no": 372, "missing": 371 , "children": [
                    { "nodeid": 371, "leaf": 0.726842761 }, 
                    { "nodeid": 372, "depth": 9, "split": "f13", "split_condition": 0.0107904654, "yes": 547, "no": 548, "missing": 547 , "children": [
                      { "nodeid": 547, "leaf": -0.090454869 }, 
                      { "nodeid": 548, "leaf": 0.258419544 }
                    ]}
                  ]}, 
                  { "nodeid": 246, "depth": 8, "split": "f3", "split_condition": -0.82042557, "yes": 373, "no": 374, "missing": 373 , "children": [
                    { "nodeid": 373, "leaf": 0.094235234 }, 
                    { "nodeid": 374, "leaf": 1.52524078 }
                  ]}
                ]}
              ]}
            ]}, 
            { "nodeid": 50, "depth": 5, "split": "f9", "split_condition": -1.31896734, "yes": 89, "no": 90, "missing": 89 , "children": [
              { "nodeid": 89, "depth": 6, "split": "f15", "split_condition": -0.754819214, "yes": 153, "no": 154, "missing": 153 , "children": [
                { "nodeid": 153, "depth": 7, "split": "f18", "split_condition": -1.73592281, "yes": 247, "no": 248, "missing": 247 , "children": [
                  { "nodeid": 247, "leaf": -1.40656841 }, 
                  { "nodeid": 248, "depth": 8, "split": "f19", "split_condition": 2.02288294, "yes": 375, "no": 376, "missing": 375 , "children": [
                    { "nodeid": 375, "depth": 9, "split": "f3", "split_condition": 0.081210345, "yes": 549, "no": 550, "missing": 549 , "children": [
                      { "nodeid": 549, "leaf": -0.217346385 }, 
                      { "nodeid": 550, "leaf": -0.786309898 }
                    ]}, 
                    { "nodeid": 376, "depth": 9, "split": "f12", "split_condition": -0.39020744, "yes": 551, "no": 552, "missing": 551 , "children": [
                      { "nodeid": 551, "leaf": -0.0382228866 }, 
                      { "nodeid": 552, "leaf": 0.211896777 }
                    ]}
                  ]}
                ]}, 
                { "nodeid": 154, "depth": 7, "split": "f0", "split_condition": -1.60073853, "yes": 249, "no": 250, "missing": 249 , "children": [
                  { "nodeid": 249, "depth": 8, "split": "f2", "split_condition": 0.491123527, "yes": 377, "no": 378, "missing": 377 , "children": [
                    { "nodeid": 377, "depth": 9, "split": "f3", "split_condition": -1.28807533, "yes": 553, "no": 554, "missing": 553 , "children": [
                      { "nodeid": 553, "leaf": -0.100161746 }, 
                      { "nodeid": 554, "leaf": -0.652192354 }
                    ]}, 
                    { "nodeid": 378, "leaf": 0.0458602905 }
                  ]}, 
                  { "nodeid": 250, "depth": 8, "split": "f10", "split_condition": -0.0795721561, "yes": 379, "no": 380, "missing": 379 , "children": [
                    { "nodeid": 379, "depth": 9, "split": "f19", "split_condition": 1.39141023, "yes": 555, "no": 556, "missing": 555 , "children": [
                      { "nodeid": 555, "leaf": 0.107757233 }, 
                      { "nodeid": 556, "leaf": 0.514729738 }
                    ]}, 
                    { "nodeid": 380, "depth": 9, "split": "f18", "split_condition": 1.01530612, "yes": 557, "no": 558, "missing": 557 , "children": [
                      { "nodeid": 557, "leaf": -0.100036919 }, 
                      { "nodeid": 558, "leaf": 0.349327862 }
                    ]}
                  ]}
                ]}
              ]}, 
              { "nodeid": 90, "depth": 6, "split": "f19", "split_condition": 1.02712166, "yes": 155, "no": 156, "missing": 155 , "children": [
                { "nodeid": 155, "depth": 7, "split": "f4", "split_condition": -0.489681065, "yes": 251, "no": 252, "missing": 251 , "children": [
                  { "nodeid": 251, "depth": 8, "split": "f17", "split_condition": 0.147865817, "yes": 381, "no": 382, "missing": 381 , "children": [
                    { "nodeid": 381, "depth": 9, "split": "f1", "split_condition": 0.0517480113, "yes": 559, "no": 560, "missing": 559 , "children": [
                      { "nodeid": 559, "leaf": -0.454950094 }, 
                      { "nodeid": 560, "leaf": 0.16341655 }
                    ]}, 
                    { "nodeid": 382, "depth": 9, "split": "f14", "split_condition": 0.46386236, "yes": 561, "no": 562, "missing": 561 , "children": [
                      { "nodeid": 561, "leaf": 0.571275532 }, 
                      { "nodeid": 562, "leaf": 0.199523926 }
                    ]}
                  ]}, 
                  { "nodeid": 252, "depth": 8, "split": "f13", "split_condition": 0.0732864439, "yes": 383, "no": 384, "missing": 383 , "children": [
                    { "nodeid": 383, "depth": 9, "split": "f2", "split_condition": -0.962807059, "yes": 563, "no": 564, "missing": 563 , "children": [
                      { "nodeid": 563, "leaf": 0.352499396 }, 
                      { "nodeid": 564, "leaf": 1.62707996 }
                    ]}, 
                    { "nodeid": 384, "depth": 9, "split": "f6", "split_condition": 0.971720099, "yes": 565, "no": 566, "missing": 565 , "children": [
                      { "nodeid": 565, "leaf": 0.893568516 }, 
                      { "nodeid": 566, "leaf": -0.167863473 }
                    ]}
                  ]}
                ]}, 
                { "nodeid": 156, "depth": 7, "split": "f3", "split_condition": -0.49902311, "yes": 253, "no": 254, "missing": 253 , "children": [
                  { "nodeid": 253, "depth": 8, "split": "f9", "split_condition": -0.90002203, "yes": 385, "no": 386, "missing": 385 , "children": [
                    { "nodeid": 385, "depth": 9, "split": "f18", "split_condition": -1.31832051, "yes": 567, "no": 568, "missing": 567 , "children": [
                      { "nodeid": 567, "leaf": -0.407279104 }, 
                      { "nodeid": 568, "leaf": 0.0629408136 }
                    ]}, 
                    { "nodeid": 386, "depth": 9, "split": "f1", "split_condition": 1.44001842, "yes": 569, "no": 570, "missing": 569 , "children": [
                      { "nodeid": 569, "leaf": -0.931187928 }, 
                      { "nodeid": 570, "leaf": 0.183055684 }
                    ]}
                  ]}, 
                  { "nodeid": 254, "depth": 8, "split": "f2", "split_condition": -0.501671791, "yes": 387, "no": 388, "missing": 387 , "children": [
                    { "nodeid": 387, "depth": 9, "split": "f18", "split_condition": 0.159521744, "yes": 571, "no": 572, "missing": 571 , "children": [
                      { "nodeid": 571, "leaf": -0.222637162 }, 
                      { "nodeid": 572, "leaf": 0.195702508 }
                    ]}, 
                    { "nodeid": 388, "depth": 9, "split": "f13", "split_condition": 1.43953133, "yes": 573, "no": 574, "missing": 573 , "children": [
                      { "nodeid": 573, "leaf": 0.620512843 }, 
                      { "nodeid": 574, "leaf": -0.645923257 }
                    ]}
                  ]}
                ]}
              ]}
            ]}
          ]}
        ]}, 
        { "nodeid": 14, "depth": 3, "split": "f3", "split_condition": 0.901569128, "yes": 27, "no": 28, "missing": 27 , "children": [
          { "nodeid": 27, "depth": 4, "split": "f4", "split_condition": -0.58946836, "yes": 51, "no": 52, "missing": 51 , "children": [
            { "nodeid": 51, "depth": 5, "split": "f15", "split_condition": -0.48434341, "yes": 91, "no": 92, "missing": 91 , "children": [
              { "nodeid": 91, "depth": 6, "split": "f9", "split_condition": 1.04025078, "yes": 157, "no": 158, "missing": 157 , "children": [
                { "nodeid": 157, "depth": 7, "split": "f14", "split_condition": -0.580632448, "yes": 255, "no": 256, "missing": 255 , "children": [
                  { "nodeid": 255, "depth": 8, "split": "f19", "split_condition": 0.658123255, "yes": 389, "no": 390, "missing": 389 , "children": [
                    { "nodeid": 389, "depth": 9, "split": "f15", "split_condition": -0.77238822, "yes": 575, "no": 576, "missing": 575 , "children": [
                      { "nodeid": 575, "leaf": -0.674142301 }, 
                      { "nodeid": 576, "leaf": -1.68303585 }
                    ]}, 
                    { "nodeid": 390, "depth": 9, "split": "f4", "split_condition": -1.34490323, "yes": 577, "no": 578, "missing": 577 , "children": [
                      { "nodeid": 577, "leaf": -0.510484636 }, 
                      { "nodeid": 578, "leaf": 0.545627356 }
                    ]}
                  ]}, 
                  { "nodeid": 256, "depth": 8, "split": "f13", "split_condition": 1.42130709, "yes": 391, "no": 392, "missing": 391 , "children": [
                    { "nodeid": 391, "depth": 9, "split": "f3", "split_condition": -1.83607984, "yes": 579, "no": 580, "missing": 579 , "children": [
                      { "nodeid": 579, "leaf": -1.04516518 }, 
                      { "nodeid": 580, "leaf": -0.211708143 }
                    ]}, 
                    { "nodeid": 392, "depth": 9, "split": "f7", "split_condition": -0.0852991641, "yes": 581, "no": 582, "missing": 581 , "children": [
                      { "nodeid": 581, "leaf": -0.0791125596 }, 
                      { "nodeid": 582, "leaf": -1.76449358 }
                    ]}
                  ]}
                ]}, 
                { "nodeid": 158, "depth": 7, "split": "f4", "split_condition": -0.918986559, "yes": 257, "no": 258, "missing": 257 , "children": [
                  { "nodeid": 257, "depth": 8, "split": "f4", "split_condition": -1.54409051, "yes": 393, "no": 394, "missing": 393 , "children": [
                    { "nodeid": 393, "depth": 9, "split": "f9", "split_condition": 2.18397737, "yes": 583, "no": 584, "missing": 583 , "children": [
                      { "nodeid": 583, "leaf": -0.38098827 }, 
                      { "nodeid": 584, "leaf": 0.149414062 }
                    ]}, 
                    { "nodeid": 394, "depth": 9, "split": "f14", "split_condition": 0.158182517, "yes": 585, "no": 586, "missing": 585 , "children": [
                      { "nodeid": 585, "leaf": 0.170917675 }, 
                      { "nodeid": 586, "leaf": 0.758233786 }
                    ]}
                  ]}, 
                  { "nodeid": 258, "depth": 8, "split": "f4", "split_condition": -0.909684062, "yes": 395, "no": 396, "missing": 395 , "children": [
                    { "nodeid": 395, "leaf": -1.5172013 }, 
                    { "nodeid": 396, "depth": 9, "split": "f1", "split_condition": -0.66052258, "yes": 587, "no": 588, "missing": 587 , "children": [
                      { "nodeid": 587, "leaf": 0.433482707 }, 
                      { "nodeid": 588, "leaf": -0.290841192 }
                    ]}
                  ]}
                ]}
              ]}, 
              { "nodeid": 92, "depth": 6, "split": "f1", "split_condition": -1.2150687, "yes": 159, "no": 160, "missing": 159 , "children": [
                { "nodeid": 159, "depth": 7, "split": "f1", "split_condition": -1.26308715, "yes": 259, "no": 260, "missing": 259 , "children": [
                  { "nodeid": 259, "depth": 8, "split": "f2", "split_condition": 1.1768856, "yes": 397, "no": 398, "missing": 397 , "children": [
                    { "nodeid": 397, "depth": 9, "split": "f7", "split_condition": 0.357954204, "yes": 589, "no": 590, "missing": 589 , "children": [
                      { "nodeid": 589, "leaf": -0.532578111 }, 
                      { "nodeid": 590, "leaf": 0.0460640229 }
                    ]}, 
                    { "nodeid": 398, "depth": 9, "split": "f12", "split_condition": -0.0732059628, "yes": 591, "no": 592, "missing": 591 , "children": [
                      { "nodeid": 591, "leaf": 0.767135739 }, 
                      { "nodeid": 592, "leaf": 0.106408693 }
                    ]}
                  ]}, 
                  { "nodeid": 260, "depth": 8, "split": "f10", "split_condition": 0.544327438, "yes": 399, "no": 400, "missing": 399 , "children": [
                    { "nodeid": 399, "depth": 9, "split": "f4", "split_condition": -1.30730629, "yes": 593, "no": 594, "missing": 593 , "children": [
                      { "nodeid": 593, "leaf": -0.281062901 }, 
                      { "nodeid": 594, "leaf": -3.1038568 }
                    ]}, 
                    { "nodeid": 400, "depth": 9, "split": "f0", "split_condition": 0.309493959, "yes": 595, "no": 596, "missing": 595 , "children": [
                      { "nodeid": 595, "leaf": 0.512280881 }, 
                      { "nodeid": 596, "leaf": -0.110431924 }
                    ]}
                  ]}
                ]}, 
                { "nodeid": 160, "depth": 7, "split": "f12", "split_condition": -2.0568018, "yes": 261, "no": 262, "missing": 261 , "children": [
                  { "nodeid": 261, "depth": 8, "split": "f0", "split_condition": 1.03825104, "yes": 401, "no": 402, "missing": 401 , "children": [
                    { "nodeid": 401, "depth": 9, "split": "f10", "split_condition": 0.67847836, "yes": 597, "no": 598, "missing": 597 , "children": [
                      { "nodeid": 597, "leaf": -2.08977962 }, 
                      { "nodeid": 598, "leaf": -0.733360529 }
                    ]}, 
                    { "nodeid": 402, "depth": 9, "split": "f1", "split_condition": -0.305903077, "yes": 599, "no": 600, "missing": 599 , "children": [
                      { "nodeid": 599, "leaf": 0.194486529 }, 
                      { "nodeid": 600, "leaf": -0.240788773 }
                    ]}
                  ]}, 
                  { "nodeid": 262, "depth": 8, "split": "f10", "split_condition": -1.18655491, "yes": 403, "no": 404, "missing": 403 , "children": [
                    { "nodeid": 403, "depth": 9, "split": "f19", "split_condition": 0.658681989, "yes": 601, "no": 602, "missing": 601 , "children": [
                      { "nodeid": 601, "leaf": -0.485418558 }, 
                      { "nodeid": 602, "leaf": 0.1827728 }
                    ]}, 
                    { "nodeid": 404, "depth": 9, "split": "f2", "split_condition": -1.93238187, "yes": 603, "no": 604, "missing": 603 , "children": [
                      { "nodeid": 603, "leaf": -0.642265677 }, 
                      { "nodeid": 604, "leaf": 0.108882122 }
                    ]}
                  ]}
                ]}
              ]}
            ]}, 
            { "nodeid": 52, "depth": 5, "split": "f12", "split_condition": 1.19487309, "yes": 93, "no": 94, "missing": 93 , "children": [
              { "nodeid": 93, "depth": 6, "split": "f1", "split_condition": 0.695103168, "yes": 161, "no": 162, "missing": 161 , "children": [
                { "nodeid": 161, "depth": 7, "split": "f14", "split_condition": 2.08246279, "yes": 263, "no": 264, "missing": 263 , "children": [
                  { "nodeid": 263, "depth": 8, "split": "f3", "split_condition": -1.49134016, "yes": 405, "no": 406, "missing": 405 , "children": [
                    { "nodeid": 405, "depth": 9, "split": "f9", "split_condition": -0.771725416, "yes": 605, "no": 606, "missing": 605 , "children": [
                      { "nodeid": 605, "leaf": 0.833384037 }, 
                      { "nodeid": 606, "leaf": -0.432932287 }
                    ]}, 
                    { "nodeid": 406, "depth": 9, "split": "f18", "split_condition": 1.23954082, "yes": 607, "no": 608, "missing": 607 , "children": [
                      { "nodeid": 607, "leaf": -0.0202406924 }, 
                      { "nodeid": 608, "leaf": 0.352049977 }
                    ]}
                  ]}, 
                  { "nodeid": 264, "depth": 8, "split": "f7", "split_condition": -0.584124744, "yes": 407, "no": 408, "missing": 407 , "children": [
                    { "nodeid": 407, "depth": 9, "split": "f14", "split_condition": 2.42452383, "yes": 609, "no": 610, "missing": 609 , "children": [
                      { "nodeid": 609, "leaf": -0.122383371 }, 
                      { "nodeid": 610, "leaf": 0.832595646 }
                    ]}, 
                    { "nodeid": 408, "depth": 9, "split": "f2", "split_condition": -0.62568295, "yes": 611, "no": 612, "missing": 611 , "children": [
                      { "nodeid": 611, "leaf": 0.0929712057 }, 
                      { "nodeid": 612, "leaf": 1.42089975 }
                    ]}
                  ]}
                ]}, 
                { "nodeid": 162, "depth": 7, "split": "f1", "split_condition": 3.94495964, "yes": 265, "no": 266, "missing": 265 , "children": [
                  { "nodeid": 265, "depth": 8, "split": "f6", "split_condition": 0.26623109, "yes": 409, "no": 410, "missing": 409 , "children": [
                    { "nodeid": 409, "depth": 9, "split": "f6", "split_condition": -0.162583619, "yes": 613, "no": 614, "missing": 613 , "children": [
                      { "nodeid": 613, "leaf": 0.2288353 }, 
                      { "nodeid": 614, "leaf": -0.103258565 }
                    ]}, 
                    { "nodeid": 410, "depth": 9, "split": "f17", "split_condition": -0.99611783, "yes": 615, "no": 616, "missing": 615 , "children": [
                      { "nodeid": 615, "leaf": -0.000652136572 }, 
                      { "nodeid": 616, "leaf": 0.474288762 }
                    ]}
                  ]}, 
                  { "nodeid": 266, "leaf": 2.60646367 }
                ]}
              ]}, 
              { "nodeid": 94, "depth": 6, "split": "f19", "split_condition": -0.440211356, "yes": 163, "no": 164, "missing": 163 , "children": [
                { "nodeid": 163, "depth": 7, "split": "f12", "split_condition": 1.52754378, "yes": 267, "no": 268, "missing": 267 , "children": [
                  { "nodeid": 267, "depth": 8, "split": "f12", "split_condition": 1.51883185, "yes": 411, "no": 412, "missing": 411 , "children": [
                    { "nodeid": 411, "depth": 9, "split": "f0", "split_condition": -0.411401272, "yes": 617, "no": 618, "missing": 617 , "children": [
                      { "nodeid": 617, "leaf": 0.521502972 }, 
                      { "nodeid": 618, "leaf": -0.0195149202 }
                    ]}, 
                    { "nodeid": 412, "leaf": 2.30948424 }
                  ]}, 
                  { "nodeid": 268, "depth": 8, "split": "f4", "split_condition": -0.464015484, "yes": 413, "no": 414, "missing": 413 , "children": [
                    { "nodeid": 413, "leaf": -1.44238675 }, 
                    { "nodeid": 414, "depth": 9, "split": "f17", "split_condition": 0.818016946, "yes": 619, "no": 620, "missing": 619 , "children": [
                      { "nodeid": 619, "leaf": -0.278880328 }, 
                      { "nodeid": 620, "leaf": 0.281598777 }
                    ]}
                  ]}
                ]}, 
                { "nodeid": 164, "depth": 7, "split": "f0", "split_condition": -0.910205603, "yes": 269, "no": 270, "missing": 269 , "children": [
                  { "nodeid": 269, "depth": 8, "split": "f4", "split_condition": 0.486821949, "yes": 415, "no": 416, "missing": 415 , "children": [
                    { "nodeid": 415, "depth": 9, "split": "f6", "split_condition": 0.830416083, "yes": 621, "no": 622, "missing": 621 , "children": [
                      { "nodeid": 621, "leaf": -0.564472795 }, 
                      { "nodeid": 622, "leaf": 0.363402903 }
                    ]}, 
                    { "nodeid": 416, "depth": 9, "split": "f7", "split_condition": -0.803781867, "yes": 623, "no": 624, "missing": 623 , "children": [
                      { "nodeid": 623, "leaf": -0.301275522 }, 
                      { "nodeid": 624, "leaf": 0.541105151 }
                    ]}
                  ]}, 
                  { "nodeid": 270, "depth": 8, "split": "f10", "split_condition": -1.68142629, "yes": 417, "no": 418, "missing": 417 , "children": [
                    { "nodeid": 417, "depth": 9, "split": "f1", "split_condition": -0.35010004, "yes": 625, "no": 626, "missing": 625 , "children": [
                      { "nodeid": 625, "leaf": 0.128337294 }, 
                      { "nodeid": 626, "leaf": -0.869341671 }
                    ]}, 
                    { "nodeid": 418, "depth": 9, "split": "f18", "split_condition": -1.41649067, "yes": 627, "no": 628, "missing": 627 , "children": [
                      { "nodeid": 627, "leaf": -0.0469197594 }, 
                      { "nodeid": 628, "leaf": 0.738180101 }
                    ]}
                  ]}
                ]}
              ]}
            ]}
          ]}, 
          { "nodeid": 28, "depth": 4, "split": "f2", "split_condition": -0.782326341, "yes": 53, "no": 54, "missing": 53 , "children": [
            { "nodeid": 53, "depth": 5, "split": "f15", "split_condition": 0.482689798, "yes": 95, "no": 96, "missing": 95 , "children": [
              { "nodeid": 95, "depth": 6, "split": "f15", "split_condition": 0.350258291, "yes": 165, "no": 166, "missing": 165 , "children": [
                { "nodeid": 165, "depth": 7, "split": "f15", "split_condition": -1.89844894, "yes": 271, "no": 272, "missing": 271 , "children": [
                  { "nodeid": 271, "depth": 8, "split": "f12", "split_condition": -0.508974791, "yes": 419, "no": 420, "missing": 419 , "children": [
                    { "nodeid": 419, "leaf": -0.35353139 }, 
                    { "nodeid": 420, "leaf": -0.920355737 }
                  ]}, 
                  { "nodeid": 272, "depth": 8, "split": "f2", "split_condition": -0.93158865, "yes": 421, "no": 422, "missing": 421 , "children": [
                    { "nodeid": 421, "depth": 9, "split": "f7", "split_condition": 0.265497893, "yes": 629, "no": 630, "missing": 629 , "children": [
                      { "nodeid": 629, "leaf": 0.224822566 }, 
                      { "nodeid": 630, "leaf": -0.166389599 }
                    ]}, 
                    { "nodeid": 422, "depth": 9, "split": "f14", "split_condition": 0.689712644, "yes": 631, "no": 632, "missing": 631 , "children": [
                      { "nodeid": 631, "leaf": -0.665115893 }, 
                      { "nodeid": 632, "leaf": 0.247529894 }
                    ]}
                  ]}
                ]}, 
                { "nodeid": 166, "depth": 7, "split": "f1", "split_condition": -0.778520346, "yes": 273, "no": 274, "missing": 273 , "children": [
                  { "nodeid": 273, "depth": 8, "split": "f0", "split_condition": -0.418645501, "yes": 423, "no": 424, "missing": 423 , "children": [
                    { "nodeid": 423, "leaf": -0.0247867592 }, 
                    { "nodeid": 424, "leaf": 0.00723819761 }
                  ]}, 
                  { "nodeid": 274, "depth": 8, "split": "f0", "split_condition": 2.17377257, "yes": 425, "no": 426, "missing": 425 , "children": [
                    { "nodeid": 425, "leaf": -1.2319957 }, 
                    { "nodeid": 426, "leaf": -0.309714526 }
                  ]}
                ]}
              ]}, 
              { "nodeid": 96, "depth": 6, "split": "f3", "split_condition": 0.980345249, "yes": 167, "no": 168, "missing": 167 , "children": [
                { "nodeid": 167, "depth": 7, "split": "f0", "split_condition": 0.0266113281, "yes": 275, "no": 276, "missing": 275 , "children": [
                  { "nodeid": 275, "leaf": -0.245788574 }, 
                  { "nodeid": 276, "leaf": 1.78772378 }
                ]}, 
                { "nodeid": 168, "depth": 7, "split": "f2", "split_condition": -0.896551549, "yes": 277, "no": 278, "missing": 277 , "children": [
                  { "nodeid": 277, "depth": 8, "split": "f7", "split_condition": -0.396793276, "yes": 427, "no": 428, "missing": 427 , "children": [
                    { "nodeid": 427, "depth": 9, "split": "f3", "split_condition": 1.04721558, "yes": 633, "no": 634, "missing": 633 , "children": [
                      { "nodeid": 633, "leaf": 0.520268261 }, 
                      { "nodeid": 634, "leaf": -0.366397411 }
                    ]}, 
                    { "nodeid": 428, "depth": 9, "split": "f7", "split_condition": 0.227956921, "yes": 635, "no": 636, "missing": 635 , "children": [
                      { "nodeid": 635, "leaf": 0.513142228 }, 
                      { "nodeid": 636, "leaf": -0.0416832939 }
                    ]}
                  ]}, 
                  { "nodeid": 278, "depth": 8, "split": "f10", "split_condition": 0.367125154, "yes": 429, "no": 430, "missing": 429 , "children": [
                    { "nodeid": 429, "depth": 9, "split": "f7", "split_condition": 1.42941642, "yes": 637, "no": 638, "missing": 637 , "children": [
                      { "nodeid": 637, "leaf": 1.21669579 }, 
                      { "nodeid": 638, "leaf": 0.388582349 }
                    ]}, 
                    { "nodeid": 430, "depth": 9, "split": "f10", "split_condition": 0.731425762, "yes": 639, "no": 640, "missing": 639 , "children": [
                      { "nodeid": 639, "leaf": 0.304906458 }, 
                      { "nodeid": 640, "leaf": -0.313311011 }
                    ]}
                  ]}
                ]}
              ]}
            ]}, 
            { "nodeid": 54, "depth": 5, "split": "f1", "split_condition": -1.9429431, "yes": 97, "no": 98, "missing": 97 , "children": [
              { "nodeid": 97, "depth": 6, "split": "f0", "split_condition": 0.0228096358, "yes": 169, "no": 170, "missing": 169 , "children": [
                { "nodeid": 169, "depth": 7, "split": "f10", "split_condition": -1.04977727, "yes": 279, "no": 280, "missing": 279 , "children": [
                  { "nodeid": 279, "leaf": 0.176976532 }, 
                  { "nodeid": 280, "depth": 8, "split": "f4", "split_condition": -0.429961681, "yes": 431, "no": 432, "missing": 431 , "children": [
                    { "nodeid": 431, "depth": 9, "split": "f0", "split_condition": -1.36002898, "yes": 641, "no": 642, "missing": 641 , "children": [
                      { "nodeid": 641, "leaf": 0.0745826736 }, 
                      { "nodeid": 642, "leaf": -0.473302931 }
                    ]}, 
                    { "nodeid": 432, "leaf": -1.26008761 }
                  ]}
                ]}, 
                { "nodeid": 170, "depth": 7, "split": "f10", "split_condition": 0.134502769, "yes": 281, "no": 282, "missing": 281 , "children": [
                  { "nodeid": 281, "depth": 8, "split": "f1", "split_condition": -2.26853228, "yes": 433, "no": 434, "missing": 433 , "children": [
                    { "nodeid": 433, "depth": 9, "split": "f0", "split_condition": 1.13315487, "yes": 643, "no": 644, "missing": 643 , "children": [
                      { "nodeid": 643, "leaf": -0.0571365356 }, 
                      { "nodeid": 644, "leaf": 0.0711586028 }
                    ]}, 
                    { "nodeid": 434, "leaf": 0.383549631 }
                  ]}, 
                  { "nodeid": 282, "depth": 8, "split": "f0", "split_condition": 0.779749334, "yes": 435, "no": 436, "missing": 435 , "children": [
                    { "nodeid": 435, "leaf": -0.569677711 }, 
                    { "nodeid": 436, "leaf": -0.0333534256 }
                  ]}
                ]}
              ]}, 
              { "nodeid": 98, "depth": 6, "split": "f19", "split_condition": -0.97748673, "yes": 171, "no": 172, "missing": 171 , "children": [
                { "nodeid": 171, "depth": 7, "split": "f18", "split_condition": -0.28763181, "yes": 283, "no": 284, "missing": 283 , "children": [
                  { "nodeid": 283, "depth": 8, "split": "f6", "split_condition": 0.746611834, "yes": 437, "no": 438, "missing": 437 , "children": [
                    { "nodeid": 437, "depth": 9, "split": "f18", "split_condition": -0.871785402, "yes": 645, "no": 646, "missing": 645 , "children": [
                      { "nodeid": 645, "leaf": -0.246850207 }, 
                      { "nodeid": 646, "leaf": -0.707795143 }
                    ]}, 
                    { "nodeid": 438, "depth": 9, "split": "f4", "split_condition": 0.344528824, "yes": 647, "no": 648, "missing": 647 , "children": [
                      { "nodeid": 647, "leaf": 0.29112789 }, 
                      { "nodeid": 648, "leaf": -0.234724522 }
                    ]}
                  ]}, 
                  { "nodeid": 284, "depth": 8, "split": "f1", "split_condition": 0.0472420938, "yes": 439, "no": 440, "missing": 439 , "children": [
                    { "nodeid": 439, "depth": 9, "split": "f12", "split_condition": -0.220307589, "yes": 649, "no": 650, "missing": 649 , "children": [
                      { "nodeid": 649, "leaf": -0.350479037 }, 
                      { "nodeid": 650, "leaf": 0.318185836 }
                    ]}, 
                    { "nodeid": 440, "depth": 9, "split": "f12", "split_condition": 1.13312411, "yes": 651, "no": 652, "missing": 651 , "children": [
                      { "nodeid": 651, "leaf": 0.754423618 }, 
                      { "nodeid": 652, "leaf": -0.129256576 }
                    ]}
                  ]}
                ]}, 
                { "nodeid": 172, "depth": 7, "split": "f14", "split_condition": 0.926133275, "yes": 285, "no": 286, "missing": 285 , "children": [
                  { "nodeid": 285, "depth": 8, "split": "f12", "split_condition": -0.945682406, "yes": 441, "no": 442, "missing": 441 , "children": [
                    { "nodeid": 441, "depth": 9, "split": "f1", "split_condition": -0.539821982, "yes": 653, "no": 654, "missing": 653 , "children": [
                      { "nodeid": 653, "leaf": 0.594890058 }, 
                      { "nodeid": 654, "leaf": -0.134084508 }
                    ]}, 
                    { "nodeid": 442, "depth": 9, "split": "f2", "split_condition": 2.79975343, "yes": 655, "no": 656, "missing": 655 , "children": [
                      { "nodeid": 655, "leaf": 0.421720415 }, 
                      { "nodeid": 656, "leaf": 2.22542644 }
                    ]}
                  ]}, 
                  { "nodeid": 286, "depth": 8, "split": "f7", "split_condition": -0.976770878, "yes": 443, "no": 444, "missing": 443 , "children": [
                    { "nodeid": 443, "depth": 9, "split": "f1", "split_condition": 0.886278689, "yes": 657, "no": 658, "missing": 657 , "children": [
                      { "nodeid": 657, "leaf": -0.00622968702 }, 
                      { "nodeid": 658, "leaf": 1.02659357 }
                    ]}, 
                    { "nodeid": 444, "depth": 9, "split": "f18", "split_condition": -1.04792917, "yes": 659, "no": 660, "missing": 659 , "children": [
                      { "nodeid": 659, "leaf": 0.0326392837 }, 
                      { "nodeid": 660, "leaf": 0.981396496 }
                    ]}
                  ]}
                ]}
              ]}
            ]}
          ]}
        ]}
      ]}
    ]}
  ]}